<?xml version="1.0"?>
<RBProject version="2009r5.1">
<block type="Module" ID="1350800691">
 <ObjName>StatusLoggerKFS</ObjName>
 <ObjContainerID>747935351</ObjContainerID>
 <IsClass>1</IsClass>
 <ItemFlags>1</ItemFlags>
 <IsInterface>0</IsInterface>
 <Compatibility></Compatibility>
 <Method>
  <ItemName>RenderTableInitCmd2</ItemName>
  <Compatibility></Compatibility>
  <Visible>1</Visible>
  <ItemSource>
   <TextEncoding>134217984</TextEncoding>
   <SourceLine>Function RenderTableInitCmd2() As String</SourceLine>
   <SourceLine>// Created 4/7/2009 by Andrew Keller</SourceLine>
   <SourceLine></SourceLine>
   <SourceLine>// renders the SQL command that creates the log messages table</SourceLine>
   <SourceLine></SourceLine>
   <SourceLine>Return "create table " + kLogDB_MSG_TableName + "( " + _</SourceLine>
   <SourceLine>kLogDB_MSG_FieldLogUID + " Integer, " + _</SourceLine>
   <SourceLine>kLogDB_MSG_FieldIndex + " Integer, " + _</SourceLine>
   <SourceLine>kLogDB_MSG_FieldMessage + " String )"</SourceLine>
   <SourceLine></SourceLine>
   <SourceLine>// done.</SourceLine>
   <SourceLine></SourceLine>
   <SourceLine>End Function</SourceLine>
  </ItemSource>
  <TextEncoding>134217984</TextEncoding>
  <AliasName></AliasName>
  <ItemFlags>1</ItemFlags>
  <Shared>0</Shared>
  <ItemParams></ItemParams>
  <ItemResult>String</ItemResult>
 </Method>
 <Method>
  <ItemName>RenderTableInitCmd1</ItemName>
  <Compatibility></Compatibility>
  <Visible>1</Visible>
  <ItemSource>
   <TextEncoding>134217984</TextEncoding>
   <SourceLine>Function RenderTableInitCmd1() As String</SourceLine>
   <SourceLine>// Created 4/6/2009 by Andrew Keller</SourceLine>
   <SourceLine></SourceLine>
   <SourceLine>// renders the SQL command that creates the primary log table</SourceLine>
   <SourceLine></SourceLine>
   <SourceLine>Return "create table " + kLogDB_PL_TableName + "( " + _</SourceLine>
   <SourceLine>kLogDB_PL_FieldUID + " Integer PRIMARY KEY NOT NULL, " + _</SourceLine>
   <SourceLine>kLogDB_PL_FieldTimestamp + " TimeStamp, " + _</SourceLine>
   <SourceLine>kLogDB_PL_FieldMicroseconds + " Int64, " + _</SourceLine>
   <SourceLine>kLogDB_PL_FieldCallingMethod + " String, " + _</SourceLine>
   <SourceLine>kLogDB_PL_FieldDebugLevel + " Integer, " + _</SourceLine>
   <SourceLine>kLogDB_PL_FieldIsError + " Boolean )"</SourceLine>
   <SourceLine></SourceLine>
   <SourceLine>// done.</SourceLine>
   <SourceLine></SourceLine>
   <SourceLine>End Function</SourceLine>
  </ItemSource>
  <TextEncoding>134217984</TextEncoding>
  <AliasName></AliasName>
  <ItemFlags>1</ItemFlags>
  <Shared>0</Shared>
  <ItemParams></ItemParams>
  <ItemResult>String</ItemResult>
 </Method>
 <Method>
  <ItemName>RenderNewMessageEntries</ItemName>
  <Compatibility></Compatibility>
  <Visible>1</Visible>
  <ItemSource>
   <TextEncoding>134217984</TextEncoding>
   <SourceLine>Function RenderNewMessageEntries(iLogEntryUID As Integer, sMessages() As String) As DatabaseRecord()</SourceLine>
   <SourceLine>// Created 4/7/2009 by Andrew Keller</SourceLine>
   <SourceLine></SourceLine>
   <SourceLine>// generates a DatabaseRecord array for inserting a list of messages</SourceLine>
   <SourceLine></SourceLine>
   <SourceLine>Dim result( -1 ) As DatabaseRecord</SourceLine>
   <SourceLine>Dim row, last As Integer</SourceLine>
   <SourceLine></SourceLine>
   <SourceLine>last = UBound( sMessages )</SourceLine>
   <SourceLine></SourceLine>
   <SourceLine>ReDim result( last )</SourceLine>
   <SourceLine></SourceLine>
   <SourceLine>For row = 0 To last</SourceLine>
   <SourceLine></SourceLine>
   <SourceLine>result( row ) = New DatabaseRecord</SourceLine>
   <SourceLine></SourceLine>
   <SourceLine>result( row ).IntegerColumn( kLogDB_MSG_FieldLogUID ) = iLogEntryUID</SourceLine>
   <SourceLine>result( row ).IntegerColumn( kLogDB_MSG_FieldIndex ) = row</SourceLine>
   <SourceLine>result( row ).BlobColumn( kLogDB_MSG_FieldMessage ) = sMessages( row )</SourceLine>
   <SourceLine></SourceLine>
   <SourceLine>Next</SourceLine>
   <SourceLine></SourceLine>
   <SourceLine>Return result</SourceLine>
   <SourceLine></SourceLine>
   <SourceLine>// done.</SourceLine>
   <SourceLine></SourceLine>
   <SourceLine>End Function</SourceLine>
  </ItemSource>
  <TextEncoding>134217984</TextEncoding>
  <AliasName></AliasName>
  <ItemFlags>1</ItemFlags>
  <Shared>0</Shared>
  <ItemParams>iLogEntryUID As Integer, sMessages() As String</ItemParams>
  <ItemResult>DatabaseRecord()</ItemResult>
 </Method>
 <Method>
  <ItemName>RenderNewLogEntry</ItemName>
  <Compatibility></Compatibility>
  <Visible>1</Visible>
  <ItemSource>
   <TextEncoding>134217984</TextEncoding>
   <SourceLine>Function RenderNewLogEntry(pk As Integer, dTime As Date, ui64Time As Int64, sMethod As String, iDebugLevel As Int8, bError As Boolean) As DatabaseRecord</SourceLine>
   <SourceLine>// Created 4/6/2009 by Andrew Keller</SourceLine>
   <SourceLine></SourceLine>
   <SourceLine>// generates a DatabaseRecord for inserting a new log item</SourceLine>
   <SourceLine></SourceLine>
   <SourceLine>Dim result As New DatabaseRecord</SourceLine>
   <SourceLine></SourceLine>
   <SourceLine>result.IntegerColumn( kLogDB_PL_FieldUID ) = pk</SourceLine>
   <SourceLine>result.DateColumn( kLogDB_PL_FieldTimestamp ) = dTime</SourceLine>
   <SourceLine>result.Int64Column( kLogDB_PL_FieldMicroseconds ) = ui64Time</SourceLine>
   <SourceLine>result.BlobColumn( kLogDB_PL_FieldCallingMethod ) = sMethod</SourceLine>
   <SourceLine>result.IntegerColumn( kLogDB_PL_FieldDebugLevel ) = iDebugLevel</SourceLine>
   <SourceLine>result.BooleanColumn( kLogDB_PL_FieldIsError ) = bError</SourceLine>
   <SourceLine></SourceLine>
   <SourceLine>Return result</SourceLine>
   <SourceLine></SourceLine>
   <SourceLine>// done.</SourceLine>
   <SourceLine></SourceLine>
   <SourceLine>End Function</SourceLine>
  </ItemSource>
  <TextEncoding>134217984</TextEncoding>
  <AliasName></AliasName>
  <ItemFlags>1</ItemFlags>
  <Shared>0</Shared>
  <ItemParams>pk As Integer, dTime As Date, ui64Time As Int64, sMethod As String, iDebugLevel As Int8, bError As Boolean</ItemParams>
  <ItemResult>DatabaseRecord</ItemResult>
 </Method>
 <Method>
  <ItemName>NewStatusReportKFS</ItemName>
  <Compatibility></Compatibility>
  <Visible>1</Visible>
  <ItemSource>
   <TextEncoding>134217984</TextEncoding>
   <SourceLine>Sub NewStatusReportKFS(sMethod As String, iDebugLevel As Int8, bError As Boolean, ParamArray sMessage As String)</SourceLine>
   <SourceLine>// Created 4/7/2009 by Andrew Keller</SourceLine>
   <SourceLine></SourceLine>
   <SourceLine>// overloaded version of NewStatusReportKFS</SourceLine>
   <SourceLine></SourceLine>
   <SourceLine>// accepts the message as a ParamArray</SourceLine>
   <SourceLine></SourceLine>
   <SourceLine>NewStatusReportKFS sMethod, iDebugLevel, bError, sMessage</SourceLine>
   <SourceLine></SourceLine>
   <SourceLine>// done.</SourceLine>
   <SourceLine></SourceLine>
   <SourceLine>End Sub</SourceLine>
  </ItemSource>
  <TextEncoding>134217984</TextEncoding>
  <AliasName></AliasName>
  <ItemFlags>0</ItemFlags>
  <Shared>0</Shared>
  <ItemParams>sMethod As String, iDebugLevel As Int8, bError As Boolean, ParamArray sMessage As String</ItemParams>
  <ItemResult></ItemResult>
 </Method>
 <Method>
  <ItemName>NewStatusReportKFS</ItemName>
  <Compatibility></Compatibility>
  <Visible>1</Visible>
  <ItemSource>
   <TextEncoding>134217984</TextEncoding>
   <SourceLine>Sub NewStatusReportKFS(sMethod As String, iDebugLevel As Int8, bError As Boolean, sMessages() As String)</SourceLine>
   <SourceLine>// Created 7/3/2007 by Andrew Keller</SourceLine>
   <SourceLine>// Modified 4/7/2009 --; now stores data in a REALSQLDatabase</SourceLine>
   <SourceLine>// Modified 4/15/2009 --; converted from module to class</SourceLine>
   <SourceLine></SourceLine>
   <SourceLine>// logs the given message, and displays it if neccessary</SourceLine>
   <SourceLine></SourceLine>
   <SourceLine>// for the debug level, 0 represents a "normal" message</SourceLine>
   <SourceLine>// or error and 9 represents full debug status.</SourceLine>
   <SourceLine></SourceLine>
   <SourceLine>// in order for a message to be displayed, the message's debug level</SourceLine>
   <SourceLine>// must be less than or equal to the current debug status.</SourceLine>
   <SourceLine></SourceLine>
   <SourceLine>If Initialize Then</SourceLine>
   <SourceLine></SourceLine>
   <SourceLine>// only store the message if it is within the debug level</SourceLine>
   <SourceLine></SourceLine>
   <SourceLine>If iDebugLevel &lt;= DebugStatus Then</SourceLine>
   <SourceLine></SourceLine>
   <SourceLine>Dim dNow As Date = New Date</SourceLine>
   <SourceLine>Dim iNow As Int64 = Microseconds</SourceLine>
   <SourceLine></SourceLine>
   <SourceLine>If logDB.AddConnectionRequestKFS Then</SourceLine>
   <SourceLine></SourceLine>
   <SourceLine>// add this entry to the database</SourceLine>
   <SourceLine></SourceLine>
   <SourceLine>Dim pk As Integer = NextPrimaryKey( kLogDB_PL_TableName )</SourceLine>
   <SourceLine></SourceLine>
   <SourceLine>logDB.InsertRecord kLogDB_PL_TableName, RenderNewLogEntry( pk, dNow, iNow, sMethod, iDebugLevel, bError )</SourceLine>
   <SourceLine>Dim addme() As DatabaseRecord = RenderNewMessageEntries( pk, sMessages )</SourceLine>
   <SourceLine>For Each d As DatabaseRecord In addme</SourceLine>
   <SourceLine>logDB.InsertRecord kLogDB_MSG_TableName, d</SourceLine>
   <SourceLine>Next</SourceLine>
   <SourceLine></SourceLine>
   <SourceLine>logDB.Commit</SourceLine>
   <SourceLine></SourceLine>
   <SourceLine>// call refresh on all the query instances</SourceLine>
   <SourceLine></SourceLine>
   <SourceLine>Dim row As Integer</SourceLine>
   <SourceLine></SourceLine>
   <SourceLine>For row = UBound( queryInstances ) DownTo 0</SourceLine>
   <SourceLine>If queryInstances( row ) &lt;&gt; Nil And queryInstances( row ).Value &lt;&gt; Nil Then</SourceLine>
   <SourceLine></SourceLine>
   <SourceLine>StatusLogQueryKFS( queryInstances( row ).Value ).Refresh</SourceLine>
   <SourceLine></SourceLine>
   <SourceLine>Else</SourceLine>
   <SourceLine></SourceLine>
   <SourceLine>queryInstances.Remove row</SourceLine>
   <SourceLine></SourceLine>
   <SourceLine>End If</SourceLine>
   <SourceLine>Next</SourceLine>
   <SourceLine></SourceLine>
   <SourceLine>logDB.ReleaseConnectionRequestKFS</SourceLine>
   <SourceLine></SourceLine>
   <SourceLine>Else</SourceLine>
   <SourceLine></SourceLine>
   <SourceLine>MsgBox "Big Fat Error:" + EndOfLine + EndOfLine + "Could not connect to the database for storing a new status report."</SourceLine>
   <SourceLine></SourceLine>
   <SourceLine>End If</SourceLine>
   <SourceLine>End If</SourceLine>
   <SourceLine>Else</SourceLine>
   <SourceLine></SourceLine>
   <SourceLine>MsgBox "Big Fat Error:" + EndOfLine + EndOfLine + "Could not initialize the logging database."</SourceLine>
   <SourceLine></SourceLine>
   <SourceLine>End If</SourceLine>
   <SourceLine></SourceLine>
   <SourceLine>// done.</SourceLine>
   <SourceLine></SourceLine>
   <SourceLine>End Sub</SourceLine>
  </ItemSource>
  <TextEncoding>134217984</TextEncoding>
  <AliasName></AliasName>
  <ItemFlags>0</ItemFlags>
  <Shared>0</Shared>
  <ItemParams>sMethod As String, iDebugLevel As Int8, bError As Boolean, sMessages() As String</ItemParams>
  <ItemResult></ItemResult>
 </Method>
 <Method>
  <ItemName>Initialize</ItemName>
  <Compatibility></Compatibility>
  <Visible>1</Visible>
  <ItemSource>
   <TextEncoding>134217984</TextEncoding>
   <SourceLine>Function Initialize(debugLevel As Int8, databaseFile As FolderItem, databasePassword As String = "") As Boolean</SourceLine>
   <SourceLine>// Created 3/13/2008 by Andrew Keller</SourceLine>
   <SourceLine>// Modified 4/15/2009 --;</SourceLine>
   <SourceLine></SourceLine>
   <SourceLine>// makes sure that this module is initialized</SourceLine>
   <SourceLine></SourceLine>
   <SourceLine>If Not InitDone Then</SourceLine>
   <SourceLine></SourceLine>
   <SourceLine>// set the debug level</SourceLine>
   <SourceLine></SourceLine>
   <SourceLine>If debugLevel &gt; -1 And debugLevel &lt; 10 Then</SourceLine>
   <SourceLine></SourceLine>
   <SourceLine>myDebugStatus = debugLevel</SourceLine>
   <SourceLine></SourceLine>
   <SourceLine>Else</SourceLine>
   <SourceLine></SourceLine>
   <SourceLine>#if DebugBuild then</SourceLine>
   <SourceLine>myDebugStatus = 2</SourceLine>
   <SourceLine>#else</SourceLine>
   <SourceLine>myDebugStatus = kDefaultDebugLevel</SourceLine>
   <SourceLine>#endif</SourceLine>
   <SourceLine></SourceLine>
   <SourceLine>End If</SourceLine>
   <SourceLine></SourceLine>
   <SourceLine>// make sure the database connection works</SourceLine>
   <SourceLine></SourceLine>
   <SourceLine>logDB = New REALSQLDatabase</SourceLine>
   <SourceLine></SourceLine>
   <SourceLine>If databaseFile &lt;&gt; Nil Then</SourceLine>
   <SourceLine></SourceLine>
   <SourceLine>logDB.DatabaseFile = databaseFile</SourceLine>
   <SourceLine></SourceLine>
   <SourceLine>If databasePassword &lt;&gt; "" Then logDB.EncryptionKey = databasePassword</SourceLine>
   <SourceLine></SourceLine>
   <SourceLine>If databaseFile.Exists Then</SourceLine>
   <SourceLine>If logDB.AddConnectionRequestKFS Then</SourceLine>
   <SourceLine></SourceLine>
   <SourceLine>logDB.ReleaseConnectionRequestKFS</SourceLine>
   <SourceLine></SourceLine>
   <SourceLine>else</SourceLine>
   <SourceLine></SourceLine>
   <SourceLine>myErrorCode = logDB.ErrorCode</SourceLine>
   <SourceLine>myErrorMsg = "Could not connect to the requested database."</SourceLine>
   <SourceLine></SourceLine>
   <SourceLine>logDB = New REALSQLDatabase</SourceLine>
   <SourceLine></SourceLine>
   <SourceLine>End If</SourceLine>
   <SourceLine>Else</SourceLine>
   <SourceLine>If logDB.CreateDatabaseFile Then</SourceLine>
   <SourceLine>If logDB.AddConnectionRequestKFS Then</SourceLine>
   <SourceLine></SourceLine>
   <SourceLine>logDB.ReleaseConnectionRequestKFS</SourceLine>
   <SourceLine></SourceLine>
   <SourceLine>Else</SourceLine>
   <SourceLine></SourceLine>
   <SourceLine>myErrorCode = logDB.ErrorCode</SourceLine>
   <SourceLine>myErrorMsg = "Could not connect to the database after creating it in the specified location."</SourceLine>
   <SourceLine></SourceLine>
   <SourceLine>logDB = New REALSQLDatabase</SourceLine>
   <SourceLine></SourceLine>
   <SourceLine>End If</SourceLine>
   <SourceLine>Else</SourceLine>
   <SourceLine></SourceLine>
   <SourceLine>myErrorCode = logDB.ErrorCode</SourceLine>
   <SourceLine>myErrorMsg = "Could not create the database at the requested location."</SourceLine>
   <SourceLine></SourceLine>
   <SourceLine>logDB = New REALSQLDatabase</SourceLine>
   <SourceLine></SourceLine>
   <SourceLine>End If</SourceLine>
   <SourceLine>End If</SourceLine>
   <SourceLine>End If</SourceLine>
   <SourceLine></SourceLine>
   <SourceLine>// make sure the database has the proper tables</SourceLine>
   <SourceLine></SourceLine>
   <SourceLine>If logDB.AddConnectionRequestKFS Then</SourceLine>
   <SourceLine>If Not logDB.HasTableKFS( kLogDB_PL_TableName ) Then</SourceLine>
   <SourceLine></SourceLine>
   <SourceLine>logDB.SQLExecute RenderTableInitCmd1</SourceLine>
   <SourceLine></SourceLine>
   <SourceLine>If logDB.Error Then</SourceLine>
   <SourceLine>MsgBox "An error occurred while adding the main tables to the logging database."</SourceLine>
   <SourceLine>End If</SourceLine>
   <SourceLine></SourceLine>
   <SourceLine>End If</SourceLine>
   <SourceLine></SourceLine>
   <SourceLine>If Not logDB.HasTableKFS( kLogDB_MSG_TableName ) Then</SourceLine>
   <SourceLine></SourceLine>
   <SourceLine>logDB.SQLExecute RenderTableInitCmd2</SourceLine>
   <SourceLine></SourceLine>
   <SourceLine>If logDB.Error Then</SourceLine>
   <SourceLine>MsgBox "An error occurred while adding the main tables to the logging database."</SourceLine>
   <SourceLine>End If</SourceLine>
   <SourceLine></SourceLine>
   <SourceLine>End If</SourceLine>
   <SourceLine></SourceLine>
   <SourceLine>InitDone = True</SourceLine>
   <SourceLine></SourceLine>
   <SourceLine>// add the current error code, if it is anything</SourceLine>
   <SourceLine></SourceLine>
   <SourceLine>If myErrorCode &lt;&gt; 0 Then</SourceLine>
   <SourceLine></SourceLine>
   <SourceLine>Me.NewStatusReportKFS "StatusLoggerKFS.Initialize( Int8, FolderItem, String )", 0, True, "An error of type " + _</SourceLine>
   <SourceLine>str( myErrorCode ) + " occurred while initializing an instance of StatusLoggerKFS:", myErrorMsg</SourceLine>
   <SourceLine></SourceLine>
   <SourceLine>End If</SourceLine>
   <SourceLine></SourceLine>
   <SourceLine>Me.NewStatusReportKFS "StatusLoggerKFS.Initialize( Int8, FolderItem, String )", 3, False, _</SourceLine>
   <SourceLine>"StatusLoggerKFS: Initialization complete.", "Debug Status set at " + str( myDebugStatus )</SourceLine>
   <SourceLine></SourceLine>
   <SourceLine>logDB.ReleaseConnectionRequestKFS</SourceLine>
   <SourceLine></SourceLine>
   <SourceLine>Else</SourceLine>
   <SourceLine></SourceLine>
   <SourceLine>MsgBox "Big Fat Error: Could not connect to the logging database after supposedly setting it up specifically so everything would work just fine."</SourceLine>
   <SourceLine></SourceLine>
   <SourceLine>End If</SourceLine>
   <SourceLine></SourceLine>
   <SourceLine>End If</SourceLine>
   <SourceLine></SourceLine>
   <SourceLine>Return InitDone</SourceLine>
   <SourceLine></SourceLine>
   <SourceLine>// done.</SourceLine>
   <SourceLine></SourceLine>
   <SourceLine>End Function</SourceLine>
  </ItemSource>
  <TextEncoding>134217984</TextEncoding>
  <AliasName></AliasName>
  <ItemFlags>0</ItemFlags>
  <Shared>0</Shared>
  <ItemParams>debugLevel As Int8, databaseFile As FolderItem, databasePassword As String = ""</ItemParams>
  <ItemResult>Boolean</ItemResult>
 </Method>
 <Method>
  <ItemName>Initialize</ItemName>
  <Compatibility></Compatibility>
  <Visible>1</Visible>
  <ItemSource>
   <TextEncoding>134217984</TextEncoding>
   <SourceLine>Function Initialize(debugLevel As Int8) As Boolean</SourceLine>
   <SourceLine>// Created 4/15/2009 by Andrew Keller</SourceLine>
   <SourceLine></SourceLine>
   <SourceLine>// initializes this module with the default settings</SourceLine>
   <SourceLine></SourceLine>
   <SourceLine>If Not InitDone Then</SourceLine>
   <SourceLine></SourceLine>
   <SourceLine>Return Initialize( debugLevel, Nil )</SourceLine>
   <SourceLine></SourceLine>
   <SourceLine>End If</SourceLine>
   <SourceLine></SourceLine>
   <SourceLine>Return True</SourceLine>
   <SourceLine></SourceLine>
   <SourceLine>// done.</SourceLine>
   <SourceLine></SourceLine>
   <SourceLine>End Function</SourceLine>
  </ItemSource>
  <TextEncoding>134217984</TextEncoding>
  <AliasName></AliasName>
  <ItemFlags>0</ItemFlags>
  <Shared>0</Shared>
  <ItemParams>debugLevel As Int8</ItemParams>
  <ItemResult>Boolean</ItemResult>
 </Method>
 <Method>
  <ItemName>Initialize</ItemName>
  <Compatibility></Compatibility>
  <Visible>1</Visible>
  <ItemSource>
   <TextEncoding>134217984</TextEncoding>
   <SourceLine>Function Initialize(databaseFile As FolderItem, databasePassword As String = "") As Boolean</SourceLine>
   <SourceLine>// Created 4/15/2009 by Andrew Keller</SourceLine>
   <SourceLine></SourceLine>
   <SourceLine>// initializes this module with the default settings</SourceLine>
   <SourceLine></SourceLine>
   <SourceLine>If Not InitDone Then</SourceLine>
   <SourceLine></SourceLine>
   <SourceLine>Return Initialize( kDefaultDebugLevel, databaseFile, databasePassword )</SourceLine>
   <SourceLine></SourceLine>
   <SourceLine>End If</SourceLine>
   <SourceLine></SourceLine>
   <SourceLine>Return True</SourceLine>
   <SourceLine></SourceLine>
   <SourceLine>// done.</SourceLine>
   <SourceLine></SourceLine>
   <SourceLine>End Function</SourceLine>
  </ItemSource>
  <TextEncoding>134217984</TextEncoding>
  <AliasName></AliasName>
  <ItemFlags>0</ItemFlags>
  <Shared>0</Shared>
  <ItemParams>databaseFile As FolderItem, databasePassword As String = ""</ItemParams>
  <ItemResult>Boolean</ItemResult>
 </Method>
 <Method>
  <ItemName>Initialize</ItemName>
  <Compatibility></Compatibility>
  <Visible>1</Visible>
  <ItemSource>
   <TextEncoding>134217984</TextEncoding>
   <SourceLine>Function Initialize() As Boolean</SourceLine>
   <SourceLine>// Created 4/15/2009 by Andrew Keller</SourceLine>
   <SourceLine></SourceLine>
   <SourceLine>// initializes this module with the default settings</SourceLine>
   <SourceLine></SourceLine>
   <SourceLine>If Not InitDone Then</SourceLine>
   <SourceLine></SourceLine>
   <SourceLine>Return Initialize( Nil )</SourceLine>
   <SourceLine></SourceLine>
   <SourceLine>End If</SourceLine>
   <SourceLine></SourceLine>
   <SourceLine>Return True</SourceLine>
   <SourceLine></SourceLine>
   <SourceLine>// done.</SourceLine>
   <SourceLine></SourceLine>
   <SourceLine>End Function</SourceLine>
  </ItemSource>
  <TextEncoding>134217984</TextEncoding>
  <AliasName></AliasName>
  <ItemFlags>0</ItemFlags>
  <Shared>0</Shared>
  <ItemParams></ItemParams>
  <ItemResult>Boolean</ItemResult>
 </Method>
 <Method>
  <ItemName>GetDBRef</ItemName>
  <Compatibility></Compatibility>
  <Visible>1</Visible>
  <ItemSource>
   <TextEncoding>134217984</TextEncoding>
   <SourceLine>Function GetDBRef() As Database</SourceLine>
   <SourceLine>// Created 4/6/2009 by Andrew Keller</SourceLine>
   <SourceLine></SourceLine>
   <SourceLine>// returns a reference to the database,</SourceLine>
   <SourceLine>// and makes sure it is initialized first</SourceLine>
   <SourceLine></SourceLine>
   <SourceLine>If Initialize Then</SourceLine>
   <SourceLine></SourceLine>
   <SourceLine>Return logDB</SourceLine>
   <SourceLine></SourceLine>
   <SourceLine>End If</SourceLine>
   <SourceLine></SourceLine>
   <SourceLine>Return Nil</SourceLine>
   <SourceLine></SourceLine>
   <SourceLine>// done.</SourceLine>
   <SourceLine></SourceLine>
   <SourceLine>End Function</SourceLine>
  </ItemSource>
  <TextEncoding>134217984</TextEncoding>
  <AliasName></AliasName>
  <ItemFlags>0</ItemFlags>
  <Shared>0</Shared>
  <ItemParams></ItemParams>
  <ItemResult>Database</ItemResult>
 </Method>
 <Method>
  <ItemName>RegisterQueryObject</ItemName>
  <Compatibility></Compatibility>
  <Visible>1</Visible>
  <ItemSource>
   <TextEncoding>134217984</TextEncoding>
   <SourceLine>Sub RegisterQueryObject(queryObject As StatusLogQueryKFS)</SourceLine>
   <SourceLine>// Created 4/15/2009 by Andrew Keller</SourceLine>
   <SourceLine></SourceLine>
   <SourceLine>// registers an instance of StatusLoggerKFS with this class</SourceLine>
   <SourceLine></SourceLine>
   <SourceLine>If qi_indexOf( queryInstances, queryObject ) = -1 Then</SourceLine>
   <SourceLine></SourceLine>
   <SourceLine>queryInstances.Append New WeakRef( queryObject )</SourceLine>
   <SourceLine></SourceLine>
   <SourceLine>End If</SourceLine>
   <SourceLine></SourceLine>
   <SourceLine>// done.</SourceLine>
   <SourceLine></SourceLine>
   <SourceLine>End Sub</SourceLine>
  </ItemSource>
  <TextEncoding>134217984</TextEncoding>
  <AliasName></AliasName>
  <ItemFlags>0</ItemFlags>
  <Shared>0</Shared>
  <ItemParams>queryObject As StatusLogQueryKFS</ItemParams>
  <ItemResult></ItemResult>
 </Method>
 <Method>
  <ItemName>UnregisterQueryObject</ItemName>
  <Compatibility></Compatibility>
  <Visible>1</Visible>
  <ItemSource>
   <TextEncoding>134217984</TextEncoding>
   <SourceLine>Sub UnregisterQueryObject(queryObject As StatusLogQueryKFS)</SourceLine>
   <SourceLine>// Created 4/15/2009 by Andrew Keller</SourceLine>
   <SourceLine></SourceLine>
   <SourceLine>// unregisters an instance of StatusLoggerKFS with this class</SourceLine>
   <SourceLine></SourceLine>
   <SourceLine>Dim row As Integer = qi_indexOf( queryInstances, queryObject )</SourceLine>
   <SourceLine></SourceLine>
   <SourceLine>While row &gt; -1</SourceLine>
   <SourceLine></SourceLine>
   <SourceLine>queryInstances.Remove row</SourceLine>
   <SourceLine></SourceLine>
   <SourceLine>row = qi_indexOf( queryInstances, queryObject )</SourceLine>
   <SourceLine></SourceLine>
   <SourceLine>Wend</SourceLine>
   <SourceLine></SourceLine>
   <SourceLine>// done.</SourceLine>
   <SourceLine></SourceLine>
   <SourceLine>End Sub</SourceLine>
  </ItemSource>
  <TextEncoding>134217984</TextEncoding>
  <AliasName></AliasName>
  <ItemFlags>0</ItemFlags>
  <Shared>0</Shared>
  <ItemParams>queryObject As StatusLogQueryKFS</ItemParams>
  <ItemResult></ItemResult>
 </Method>
 <Method>
  <ItemName>ErrorCode</ItemName>
  <Compatibility></Compatibility>
  <Visible>1</Visible>
  <ItemSource>
   <TextEncoding>134217984</TextEncoding>
   <SourceLine>Function ErrorCode() As Integer</SourceLine>
   <SourceLine>// Created 4/15/2009 by Andrew Keller</SourceLine>
   <SourceLine></SourceLine>
   <SourceLine>// returns the current error message, exactly the way it</SourceLine>
   <SourceLine>// is, without checking the init status of the database</SourceLine>
   <SourceLine></SourceLine>
   <SourceLine>Return myErrorCode</SourceLine>
   <SourceLine></SourceLine>
   <SourceLine>// done.</SourceLine>
   <SourceLine></SourceLine>
   <SourceLine>End Function</SourceLine>
  </ItemSource>
  <TextEncoding>134217984</TextEncoding>
  <AliasName></AliasName>
  <ItemFlags>0</ItemFlags>
  <Shared>0</Shared>
  <ItemParams></ItemParams>
  <ItemResult>Integer</ItemResult>
 </Method>
 <Method>
  <ItemName>ErrorMessage</ItemName>
  <Compatibility></Compatibility>
  <Visible>1</Visible>
  <ItemSource>
   <TextEncoding>134217984</TextEncoding>
   <SourceLine>Function ErrorMessage() As String</SourceLine>
   <SourceLine>// Created 4/15/2009 by Andrew Keller</SourceLine>
   <SourceLine></SourceLine>
   <SourceLine>// returns the current error message, exactly the way it</SourceLine>
   <SourceLine>// is, without checking the init status of the database</SourceLine>
   <SourceLine></SourceLine>
   <SourceLine>Return myErrorMsg</SourceLine>
   <SourceLine></SourceLine>
   <SourceLine>// done.</SourceLine>
   <SourceLine></SourceLine>
   <SourceLine>End Function</SourceLine>
  </ItemSource>
  <TextEncoding>134217984</TextEncoding>
  <AliasName></AliasName>
  <ItemFlags>0</ItemFlags>
  <Shared>0</Shared>
  <ItemParams></ItemParams>
  <ItemResult>String</ItemResult>
 </Method>
 <Method>
  <ItemName>qi_indexOf</ItemName>
  <Compatibility></Compatibility>
  <Visible>1</Visible>
  <ItemSource>
   <TextEncoding>134217984</TextEncoding>
   <SourceLine>Function qi_indexOf(ary() As WeakRef, search As StatusLogQueryKFS) As Integer</SourceLine>
   <SourceLine>// Created 4/15/2009 by Andrew Keller</SourceLine>
   <SourceLine></SourceLine>
   <SourceLine>// finds the first occurance of search in ary</SourceLine>
   <SourceLine></SourceLine>
   <SourceLine>Dim row, last As Integer</SourceLine>
   <SourceLine></SourceLine>
   <SourceLine>last = UBound( ary )</SourceLine>
   <SourceLine></SourceLine>
   <SourceLine>For row = 0 To last</SourceLine>
   <SourceLine></SourceLine>
   <SourceLine>If ary( row ) &lt;&gt; Nil Then</SourceLine>
   <SourceLine></SourceLine>
   <SourceLine>If ary( row ).Value &lt;&gt; Nil Then</SourceLine>
   <SourceLine></SourceLine>
   <SourceLine>If StatusLogQueryKFS( ary( row ).Value ) = search Then</SourceLine>
   <SourceLine></SourceLine>
   <SourceLine>Return row</SourceLine>
   <SourceLine></SourceLine>
   <SourceLine>End If</SourceLine>
   <SourceLine></SourceLine>
   <SourceLine>End If</SourceLine>
   <SourceLine></SourceLine>
   <SourceLine>End If</SourceLine>
   <SourceLine></SourceLine>
   <SourceLine>Next</SourceLine>
   <SourceLine></SourceLine>
   <SourceLine>Return -1</SourceLine>
   <SourceLine></SourceLine>
   <SourceLine>// done.</SourceLine>
   <SourceLine></SourceLine>
   <SourceLine>End Function</SourceLine>
  </ItemSource>
  <TextEncoding>134217984</TextEncoding>
  <AliasName></AliasName>
  <ItemFlags>1</ItemFlags>
  <Shared>0</Shared>
  <ItemParams>ary() As WeakRef, search As StatusLogQueryKFS</ItemParams>
  <ItemResult>Integer</ItemResult>
 </Method>
 <Method>
  <ItemName>GetLogTableSchema</ItemName>
  <Compatibility></Compatibility>
  <Visible>1</Visible>
  <ItemSource>
   <TextEncoding>134217984</TextEncoding>
   <SourceLine>Function GetLogTableSchema() As String()</SourceLine>
   <SourceLine>// Created 4/6/2009 by Andrew Keller</SourceLine>
   <SourceLine>// Modified 4/15/2009 --;</SourceLine>
   <SourceLine></SourceLine>
   <SourceLine>// returns a real-time string array containing</SourceLine>
   <SourceLine>// the fields in the main log table</SourceLine>
   <SourceLine></SourceLine>
   <SourceLine>Dim result(-1) As String</SourceLine>
   <SourceLine></SourceLine>
   <SourceLine>If logDB.AddConnectionRequestKFS Then</SourceLine>
   <SourceLine></SourceLine>
   <SourceLine>Dim rs As RecordSet = logDB.FieldSchema( kLogDB_PL_TableName )</SourceLine>
   <SourceLine></SourceLine>
   <SourceLine>If rs &lt;&gt; Nil Then</SourceLine>
   <SourceLine></SourceLine>
   <SourceLine>While Not rs.EOF</SourceLine>
   <SourceLine></SourceLine>
   <SourceLine>result.Append rs.Field( "ColumnName" ).StringValue</SourceLine>
   <SourceLine></SourceLine>
   <SourceLine>rs.MoveNext</SourceLine>
   <SourceLine></SourceLine>
   <SourceLine>Wend</SourceLine>
   <SourceLine></SourceLine>
   <SourceLine>End If</SourceLine>
   <SourceLine></SourceLine>
   <SourceLine>logDB.ReleaseConnectionRequestKFS</SourceLine>
   <SourceLine></SourceLine>
   <SourceLine>End If</SourceLine>
   <SourceLine></SourceLine>
   <SourceLine>Return result</SourceLine>
   <SourceLine></SourceLine>
   <SourceLine>// done.</SourceLine>
   <SourceLine></SourceLine>
   <SourceLine>End Function</SourceLine>
  </ItemSource>
  <TextEncoding>134217984</TextEncoding>
  <AliasName></AliasName>
  <ItemFlags>0</ItemFlags>
  <Shared>0</Shared>
  <ItemParams></ItemParams>
  <ItemResult>String()</ItemResult>
 </Method>
 <Method>
  <ItemName>DebugStatus</ItemName>
  <Compatibility></Compatibility>
  <Visible>1</Visible>
  <ItemSource>
   <TextEncoding>134217984</TextEncoding>
   <SourceLine>Function DebugStatus() As Int8</SourceLine>
   <SourceLine>// Created 4/15/2009 by Andrew Keller</SourceLine>
   <SourceLine></SourceLine>
   <SourceLine>// returns the current debug status that this class is using</SourceLine>
   <SourceLine></SourceLine>
   <SourceLine>If Initialize Then</SourceLine>
   <SourceLine></SourceLine>
   <SourceLine>Return myDebugStatus</SourceLine>
   <SourceLine></SourceLine>
   <SourceLine>Else</SourceLine>
   <SourceLine></SourceLine>
   <SourceLine>Return -1</SourceLine>
   <SourceLine></SourceLine>
   <SourceLine>End If</SourceLine>
   <SourceLine></SourceLine>
   <SourceLine>// done.</SourceLine>
   <SourceLine></SourceLine>
   <SourceLine>End Function</SourceLine>
  </ItemSource>
  <TextEncoding>134217984</TextEncoding>
  <AliasName></AliasName>
  <ItemFlags>0</ItemFlags>
  <Shared>0</Shared>
  <ItemParams></ItemParams>
  <ItemResult>Int8</ItemResult>
 </Method>
 <Method>
  <ItemName>DebugStatus</ItemName>
  <Compatibility></Compatibility>
  <Visible>1</Visible>
  <ItemSource>
   <TextEncoding>134217984</TextEncoding>
   <SourceLine>Sub DebugStatus(Assigns newStatus As Int8)</SourceLine>
   <SourceLine>// Created 4/15/2009 by Andrew Keller</SourceLine>
   <SourceLine></SourceLine>
   <SourceLine>// sets the debug status that this class is using</SourceLine>
   <SourceLine></SourceLine>
   <SourceLine>If InitDone Then</SourceLine>
   <SourceLine></SourceLine>
   <SourceLine>myDebugStatus = newStatus</SourceLine>
   <SourceLine></SourceLine>
   <SourceLine>Me.NewStatusReportKFS "StatusLoggerKFS.DebugStatus( Int8 )", 3, False, _</SourceLine>
   <SourceLine>"Debug Status changed to " + str( myDebugStatus )</SourceLine>
   <SourceLine></SourceLine>
   <SourceLine>Else</SourceLine>
   <SourceLine></SourceLine>
   <SourceLine>Call Initialize( newStatus )</SourceLine>
   <SourceLine></SourceLine>
   <SourceLine>End If</SourceLine>
   <SourceLine></SourceLine>
   <SourceLine>// done.</SourceLine>
   <SourceLine></SourceLine>
   <SourceLine>End Sub</SourceLine>
  </ItemSource>
  <TextEncoding>134217984</TextEncoding>
  <AliasName></AliasName>
  <ItemFlags>0</ItemFlags>
  <Shared>0</Shared>
  <ItemParams>Assigns newStatus As Int8</ItemParams>
  <ItemResult></ItemResult>
 </Method>
 <Method>
  <ItemName>Constructor</ItemName>
  <Compatibility></Compatibility>
  <Visible>1</Visible>
  <ItemSource>
   <TextEncoding>134217984</TextEncoding>
   <SourceLine>Sub Constructor()</SourceLine>
   <SourceLine>// Created 4/15/2009 by Andrew Keller</SourceLine>
   <SourceLine></SourceLine>
   <SourceLine>// initialize properties</SourceLine>
   <SourceLine></SourceLine>
   <SourceLine>myStartupTime = New Date</SourceLine>
   <SourceLine></SourceLine>
   <SourceLine>// done.</SourceLine>
   <SourceLine></SourceLine>
   <SourceLine>End Sub</SourceLine>
  </ItemSource>
  <TextEncoding>134217984</TextEncoding>
  <AliasName></AliasName>
  <ItemFlags>0</ItemFlags>
  <Shared>0</Shared>
  <ItemParams></ItemParams>
  <ItemResult></ItemResult>
 </Method>
 <Method>
  <ItemName>StartupTime</ItemName>
  <Compatibility></Compatibility>
  <Visible>1</Visible>
  <ItemSource>
   <TextEncoding>134217984</TextEncoding>
   <SourceLine>Function StartupTime() As Date</SourceLine>
   <SourceLine>// Created 4/15/2009 by Andrew Keller</SourceLine>
   <SourceLine></SourceLine>
   <SourceLine>// returns the startup time of this class</SourceLine>
   <SourceLine></SourceLine>
   <SourceLine>Return myStartupTime</SourceLine>
   <SourceLine></SourceLine>
   <SourceLine>// done.</SourceLine>
   <SourceLine></SourceLine>
   <SourceLine>End Function</SourceLine>
  </ItemSource>
  <TextEncoding>134217984</TextEncoding>
  <AliasName></AliasName>
  <ItemFlags>0</ItemFlags>
  <Shared>0</Shared>
  <ItemParams></ItemParams>
  <ItemResult>Date</ItemResult>
 </Method>
 <Method>
  <ItemName>NextPrimaryKey</ItemName>
  <Compatibility></Compatibility>
  <Visible>1</Visible>
  <ItemSource>
   <TextEncoding>134217984</TextEncoding>
   <SourceLine>Function NextPrimaryKey(tableName As String) As Integer</SourceLine>
   <SourceLine>// Created 4/15/2009 by Andrew Keller</SourceLine>
   <SourceLine></SourceLine>
   <SourceLine>// returns a unique primary key value for</SourceLine>
   <SourceLine>// the given table in this database</SourceLine>
   <SourceLine></SourceLine>
   <SourceLine>Static cache As New Dictionary</SourceLine>
   <SourceLine>Dim result As Integer = -1</SourceLine>
   <SourceLine></SourceLine>
   <SourceLine>// get old value</SourceLine>
   <SourceLine></SourceLine>
   <SourceLine>If cache.HasKey( tableName ) Then</SourceLine>
   <SourceLine></SourceLine>
   <SourceLine>result = cache.Value( tableName )</SourceLine>
   <SourceLine></SourceLine>
   <SourceLine>Else</SourceLine>
   <SourceLine></SourceLine>
   <SourceLine>If logDB.AddConnectionRequestKFS Then</SourceLine>
   <SourceLine></SourceLine>
   <SourceLine>Dim rs As RecordSet = logDB.SQLSelect( "select " + kLogDB_PL_FieldUID + " from " + kLogDB_PL_TableName + _</SourceLine>
   <SourceLine>" order by " + kLogDB_PL_FieldUID + " desc limit 1" )</SourceLine>
   <SourceLine></SourceLine>
   <SourceLine>If rs &lt;&gt; Nil Then</SourceLine>
   <SourceLine>If Not rs.EOF Then</SourceLine>
   <SourceLine></SourceLine>
   <SourceLine>result = rs.Field( kLogDB_PL_FieldUID ).IntegerValue</SourceLine>
   <SourceLine></SourceLine>
   <SourceLine>End If</SourceLine>
   <SourceLine>End If</SourceLine>
   <SourceLine></SourceLine>
   <SourceLine>logDB.ReleaseConnectionRequestKFS</SourceLine>
   <SourceLine></SourceLine>
   <SourceLine>End If</SourceLine>
   <SourceLine>End If</SourceLine>
   <SourceLine></SourceLine>
   <SourceLine>// increment</SourceLine>
   <SourceLine></SourceLine>
   <SourceLine>result = result + 1</SourceLine>
   <SourceLine></SourceLine>
   <SourceLine>// remember</SourceLine>
   <SourceLine></SourceLine>
   <SourceLine>cache.Value( tableName ) = result</SourceLine>
   <SourceLine></SourceLine>
   <SourceLine>// return result</SourceLine>
   <SourceLine></SourceLine>
   <SourceLine>Return result</SourceLine>
   <SourceLine></SourceLine>
   <SourceLine>// done.</SourceLine>
   <SourceLine></SourceLine>
   <SourceLine>End Function</SourceLine>
  </ItemSource>
  <TextEncoding>134217984</TextEncoding>
  <AliasName></AliasName>
  <ItemFlags>0</ItemFlags>
  <Shared>0</Shared>
  <ItemParams>tableName As String</ItemParams>
  <ItemResult>Integer</ItemResult>
 </Method>
 <Property>
  <ItemName>myDebugStatus</ItemName>
  <Compatibility></Compatibility>
  <Visible>1</Visible>
  <ItemSource>
   <TextEncoding>134217984</TextEncoding>
   <SourceLine>myDebugStatus As Int8</SourceLine>
   <SourceLine></SourceLine>
  </ItemSource>
  <TextEncoding>134217984</TextEncoding>
  <ItemDeclaration>myDebugStatus As Int8</ItemDeclaration>
  <ItemFlags>1</ItemFlags>
  <Shared>0</Shared>
 </Property>
 <Property>
  <ItemName>InitDone</ItemName>
  <Compatibility></Compatibility>
  <Visible>1</Visible>
  <ItemSource>
   <TextEncoding>134217984</TextEncoding>
   <SourceLine>InitDone As Boolean</SourceLine>
   <SourceLine></SourceLine>
  </ItemSource>
  <TextEncoding>134217984</TextEncoding>
  <ItemDeclaration>InitDone As Boolean</ItemDeclaration>
  <ItemFlags>33</ItemFlags>
  <Shared>0</Shared>
 </Property>
 <Property>
  <ItemName>logDB</ItemName>
  <Compatibility></Compatibility>
  <Visible>1</Visible>
  <ItemSource>
   <TextEncoding>134217984</TextEncoding>
   <SourceLine>logDB As REALSQLDatabase</SourceLine>
   <SourceLine></SourceLine>
  </ItemSource>
  <TextEncoding>134217984</TextEncoding>
  <ItemDeclaration>logDB As REALSQLDatabase</ItemDeclaration>
  <ItemFlags>1</ItemFlags>
  <Shared>0</Shared>
 </Property>
 <Property>
  <ItemName>queryInstances()</ItemName>
  <Compatibility></Compatibility>
  <Visible>1</Visible>
  <ItemSource>
   <TextEncoding>134217984</TextEncoding>
   <SourceLine>queryInstances() As WeakRef</SourceLine>
   <SourceLine></SourceLine>
  </ItemSource>
  <TextEncoding>134217984</TextEncoding>
  <ItemDeclaration>queryInstances() As WeakRef</ItemDeclaration>
  <ItemFlags>1</ItemFlags>
  <Shared>0</Shared>
 </Property>
 <Property>
  <ItemName>myErrorCode</ItemName>
  <Compatibility></Compatibility>
  <Visible>1</Visible>
  <ItemSource>
   <TextEncoding>134217984</TextEncoding>
   <SourceLine>myErrorCode As Integer</SourceLine>
   <SourceLine></SourceLine>
  </ItemSource>
  <TextEncoding>134217984</TextEncoding>
  <ItemDeclaration>myErrorCode As Integer</ItemDeclaration>
  <ItemFlags>1</ItemFlags>
  <Shared>0</Shared>
 </Property>
 <Property>
  <ItemName>myErrorMsg</ItemName>
  <Compatibility></Compatibility>
  <Visible>1</Visible>
  <ItemSource>
   <TextEncoding>134217984</TextEncoding>
   <SourceLine>myErrorMsg As String</SourceLine>
   <SourceLine></SourceLine>
  </ItemSource>
  <TextEncoding>134217984</TextEncoding>
  <ItemDeclaration>myErrorMsg As String</ItemDeclaration>
  <ItemFlags>1</ItemFlags>
  <Shared>0</Shared>
 </Property>
 <Property>
  <ItemName>myStartupTime</ItemName>
  <Compatibility></Compatibility>
  <Visible>1</Visible>
  <ItemSource>
   <TextEncoding>134217984</TextEncoding>
   <SourceLine>myStartupTime As Date</SourceLine>
   <SourceLine></SourceLine>
  </ItemSource>
  <TextEncoding>134217984</TextEncoding>
  <ItemDeclaration>myStartupTime As Date</ItemDeclaration>
  <ItemFlags>1</ItemFlags>
  <Shared>0</Shared>
 </Property>
 <ViewBehavior>
  <ViewProperty>
   <ObjName>Name</ObjName>
   <Visible>1</Visible>
   <PropertyGroup>ID</PropertyGroup>
   <InheritsFrom>Object</InheritsFrom>
  </ViewProperty>
  <ViewProperty>
   <ObjName>Index</ObjName>
   <Visible>1</Visible>
   <PropertyGroup>ID</PropertyGroup>
   <PropertyValue>-2147483648</PropertyValue>
   <InheritsFrom>Object</InheritsFrom>
  </ViewProperty>
  <ViewProperty>
   <ObjName>Super</ObjName>
   <Visible>1</Visible>
   <PropertyGroup>ID</PropertyGroup>
   <InheritsFrom>Object</InheritsFrom>
  </ViewProperty>
  <ViewProperty>
   <ObjName>Left</ObjName>
   <Visible>1</Visible>
   <PropertyGroup>Position</PropertyGroup>
   <PropertyValue>0</PropertyValue>
   <InheritsFrom>Object</InheritsFrom>
  </ViewProperty>
  <ViewProperty>
   <ObjName>Top</ObjName>
   <Visible>1</Visible>
   <PropertyGroup>Position</PropertyGroup>
   <PropertyValue>0</PropertyValue>
   <InheritsFrom>Object</InheritsFrom>
  </ViewProperty>
 </ViewBehavior>
 <Constant>
  <ItemName>kLogDB_PL_TableName</ItemName>
  <Compatibility></Compatibility>
  <Visible>1</Visible>
  <TextEncoding>134217984</TextEncoding>
  <ItemName>kLogDB_PL_TableName</ItemName>
  <ItemType>0</ItemType>
  <ItemDef>primary_log</ItemDef>
  <ItemFlags>0</ItemFlags>
 </Constant>
 <Constant>
  <ItemName>kLogDB_PL_FieldUID</ItemName>
  <Compatibility></Compatibility>
  <Visible>1</Visible>
  <TextEncoding>134217984</TextEncoding>
  <ItemName>kLogDB_PL_FieldUID</ItemName>
  <ItemType>0</ItemType>
  <ItemDef>id</ItemDef>
  <ItemFlags>0</ItemFlags>
 </Constant>
 <Constant>
  <ItemName>kLogDB_PL_FieldTimestamp</ItemName>
  <Compatibility></Compatibility>
  <Visible>1</Visible>
  <TextEncoding>134217984</TextEncoding>
  <ItemName>kLogDB_PL_FieldTimestamp</ItemName>
  <ItemType>0</ItemType>
  <ItemDef>timestamp</ItemDef>
  <ItemFlags>0</ItemFlags>
 </Constant>
 <Constant>
  <ItemName>kLogDB_PL_FieldMicroseconds</ItemName>
  <Compatibility></Compatibility>
  <Visible>1</Visible>
  <TextEncoding>134217984</TextEncoding>
  <ItemName>kLogDB_PL_FieldMicroseconds</ItemName>
  <ItemType>0</ItemType>
  <ItemDef>microseconds</ItemDef>
  <ItemFlags>0</ItemFlags>
 </Constant>
 <Constant>
  <ItemName>kLogDB_PL_FieldIsError</ItemName>
  <Compatibility></Compatibility>
  <Visible>1</Visible>
  <TextEncoding>134217984</TextEncoding>
  <ItemName>kLogDB_PL_FieldIsError</ItemName>
  <ItemType>0</ItemType>
  <ItemDef>is_error</ItemDef>
  <ItemFlags>0</ItemFlags>
 </Constant>
 <Constant>
  <ItemName>kLogDB_PL_FieldDebugLevel</ItemName>
  <Compatibility></Compatibility>
  <Visible>1</Visible>
  <TextEncoding>134217984</TextEncoding>
  <ItemName>kLogDB_PL_FieldDebugLevel</ItemName>
  <ItemType>0</ItemType>
  <ItemDef>debug_level</ItemDef>
  <ItemFlags>0</ItemFlags>
 </Constant>
 <Constant>
  <ItemName>kLogDB_PL_FieldCallingMethod</ItemName>
  <Compatibility></Compatibility>
  <Visible>1</Visible>
  <TextEncoding>134217984</TextEncoding>
  <ItemName>kLogDB_PL_FieldCallingMethod</ItemName>
  <ItemType>0</ItemType>
  <ItemDef>calling_method</ItemDef>
  <ItemFlags>0</ItemFlags>
 </Constant>
 <Constant>
  <ItemName>kLogDB_MSG_TableName</ItemName>
  <Compatibility></Compatibility>
  <Visible>1</Visible>
  <TextEncoding>134217984</TextEncoding>
  <ItemName>kLogDB_MSG_TableName</ItemName>
  <ItemType>0</ItemType>
  <ItemDef>log_messages</ItemDef>
  <ItemFlags>0</ItemFlags>
 </Constant>
 <Constant>
  <ItemName>kLogDB_MSG_FieldMessage</ItemName>
  <Compatibility></Compatibility>
  <Visible>1</Visible>
  <TextEncoding>134217984</TextEncoding>
  <ItemName>kLogDB_MSG_FieldMessage</ItemName>
  <ItemType>0</ItemType>
  <ItemDef>message</ItemDef>
  <ItemFlags>0</ItemFlags>
 </Constant>
 <Constant>
  <ItemName>kLogDB_MSG_FieldLogUID</ItemName>
  <Compatibility></Compatibility>
  <Visible>1</Visible>
  <TextEncoding>134217984</TextEncoding>
  <ItemName>kLogDB_MSG_FieldLogUID</ItemName>
  <ItemType>0</ItemType>
  <ItemDef>log_link</ItemDef>
  <ItemFlags>0</ItemFlags>
 </Constant>
 <Constant>
  <ItemName>kLogDB_MSG_FieldIndex</ItemName>
  <Compatibility></Compatibility>
  <Visible>1</Visible>
  <TextEncoding>134217984</TextEncoding>
  <ItemName>kLogDB_MSG_FieldIndex</ItemName>
  <ItemType>0</ItemType>
  <ItemDef>findex</ItemDef>
  <ItemFlags>0</ItemFlags>
 </Constant>
 <Constant>
  <ItemName>kDefaultDebugLevel</ItemName>
  <Compatibility></Compatibility>
  <Visible>1</Visible>
  <TextEncoding>134217984</TextEncoding>
  <ItemName>kDefaultDebugLevel</ItemName>
  <ItemType>2</ItemType>
  <ItemDef>5</ItemDef>
  <ItemFlags>0</ItemFlags>
 </Constant>
</block>
</RBProject>
